{
 "id": 1663,
 "displayOs": "ALL",
 "category": "NEW",
 "subject": "【補填】緊急メンテナンス、不具合のお詫び",
 "text": "『マギアレコード 魔法少女まどか☆マギカ外伝』をご利用いただき誠にありがとうございます。<br />\r\n<br />\r\n下記の緊急メンテナンス、不具合のお詫びとして、2月21日17:00に補填をいたしました。<br />\r\n<br />\r\n<p class=\"newsHeadUnder\">■対象のお客様</p>\r\n2019年11月13日以降に1度でもログインしたことがあり、「第1部1章2話 BATTLE2」を<br />\r\nすでにクリアしているお客様<br />\r\n<br />\r\n<p class=\"newsHeadUnder\">■補填内容</p>\r\n・マギアストーン 15個<br />\r\n・AP回復薬2個<br />\r\n　<span class=\"c_red\">※プレゼントボックスよりお受け取りください。</span><br />\r\n<br />\r\n詳細につきましては、以下のお知らせをご参照ください。<br />\r\n＞お知らせ：<br />\r\n<span class=\"otherNews\" data-newsId=\"1658\">【緊急メンテナンス】終了いたしました。2月17日16:00～16:30</span><br />\r\n<span class=\"otherNews\" data-newsId=\"1657\">【不具合修正】2月15日00:10時点</span><br />\r\n<br />\r\nお客様にはご迷惑をおかけしましたことをお詫び申し上げます。<br />\r\n<br />\r\n今後とも『マギアレコード 魔法少女まどか☆マギカ外伝』をよろしくお願いいたします。<br />",
 "htmlPath": "",
 "imgPath": "",
 "hiddenUnderMaintenance": false,
 "startAt": "2020-02-21 17:00:00",
 "endAt": "2030-02-21 23:59:59",
 "sortKey": 16630
}